calculations_analysis/__init__.py
calculations_analysis/analysis_fca.py
feedback_context_analysis-1.0.0.dist-info/METADATA
feedback_context_analysis-1.0.0.dist-info/WHEEL
feedback_context_analysis-1.0.0.dist-info/top_level.txt
feedback_context_analysis-1.0.0.dist-info/RECORD
